apkpatcher/__init__.py
apkpatcher/__main__.py
apkpatcher/cli.py
apkpatcher/conf.py
apkpatcher/smalipatching.py
apkpatcher/zipalign.py
apkpatcher-0.1.37.dist-info/LICENSE
apkpatcher-0.1.37.dist-info/METADATA
apkpatcher-0.1.37.dist-info/WHEEL
apkpatcher-0.1.37.dist-info/entry_points.txt
apkpatcher-0.1.37.dist-info/top_level.txt
apkpatcher-0.1.37.dist-info/RECORD
