Metadata-Version: 2.1
Name: apkpatcher
Version: 0.1.37
Summary: Tool use as library or in cli to patch an APK, inject some libraries inside the APK or add a custom certificate
Author-email: "Benoit Forgette (MadSquirrel)" <benoit.forgette@ci-yow.com>
Maintainer-email: "Benoit Forgette (MadSquirrel)" <benoit.forgette@ci-yow.com>
License: GNU GENERAL PUBLIC LICENSE
Project-URL: Homepage, https://ci-yow.com
Project-URL: Repository, https://gitlab.com/MadSquirrels/mobile/apkpatcher
Project-URL: Documentation, https://apkpatcher.ci-yow.com
Project-URL: Issues, https://gitlab.com/MadSquirrels/mobile/apkpatcher/-/issues
Classifier: Development Status :: 4 - Beta
Classifier: Programming Language :: Python
Requires-Python: >=3.9
License-File: LICENSE
Requires-Dist: pyaxml (==0.0.*)
Requires-Dist: pysmali (==0.2.8)
Requires-Dist: pyjnius (==1.7.0)
Requires-Dist: requests
Requires-Dist: packaging
